<?xml version="1.0" encoding="utf-8"?>
<Defs>
<ThingDef ParentName="LeatherBase">
    <defName>Leather_Lapin</defName>
    <label>라핀 가죽</label>
    <description>라핀 가죽이라니 자닌해 ㅠㅠ.</description>
    <graphicData>
      <color>(211,194,143)</color>
    </graphicData>
    <statBases>
      <MarketValue>4.2</MarketValue>
      <StuffPower_Armor_Sharp>0.64</StuffPower_Armor_Sharp>
      <StuffPower_Insulation_Cold>12</StuffPower_Insulation_Cold>
      <StuffPower_Insulation_Heat>12</StuffPower_Insulation_Heat>
    </statBases>
    <stuffProps>
      <color>(211,194,143)</color>
      <commonality>0.0025</commonality>
    </stuffProps>
  </ThingDef>

  </Defs>